eagpytorch/__init__.py
eagpytorch/_base_ApproximateGP.py
eagpytorch/_base_ExactGP.py
eagpytorch/_const.py
eagpytorch/utils.py
eagpytorch/Classifier/_Approximate.py
eagpytorch/Classifier/_Exact.py
eagpytorch/Classifier/__init__.py
eagpytorch/Regressor/_Approximate.py
eagpytorch/Regressor/_Exact.py
eagpytorch/Regressor/__init__.py
eagpytorch/_likelihoods/__init__.py
eagpytorch/_likelihoods/_poisson_likelihood.py
eagpytorch-0.1.2.dist-info/LICENSE
eagpytorch-0.1.2.dist-info/METADATA
eagpytorch-0.1.2.dist-info/WHEEL
eagpytorch-0.1.2.dist-info/top_level.txt
eagpytorch-0.1.2.dist-info/RECORD
